data_check/__init__.py
data_check/config.py
data_check/data_check.py
data_check/date.py
data_check/exceptions.py
data_check/file_ops.py
data_check/py.typed
data_check/result.py
data_check/runner.py
data_check/checks/__init__.py
data_check/checks/base_check.py
data_check/checks/csv_check.py
data_check/checks/empty_set_check.py
data_check/checks/excel_check.py
data_check/checks/generator.py
data_check/checks/path_not_exists.py
data_check/checks/sql_base_check.py
data_check/checks/table_check.py
data_check/checks/pipeline_check/__init__.py
data_check/checks/pipeline_check/pipeline_check.py
data_check/checks/pipeline_check/pipeline_model.py
data_check/checks/pipeline_check/steps/__init__.py
data_check/checks/pipeline_check/steps/always_run_step.py
data_check/checks/pipeline_check/steps/append_step.py
data_check/checks/pipeline_check/steps/breakpoint_step.py
data_check/checks/pipeline_check/steps/check_step.py
data_check/checks/pipeline_check/steps/cmd_step.py
data_check/checks/pipeline_check/steps/fake_step.py
data_check/checks/pipeline_check/steps/load_step.py
data_check/checks/pipeline_check/steps/ping_step.py
data_check/checks/pipeline_check/steps/run_step.py
data_check/checks/pipeline_check/steps/sql_step.py
data_check/checks/pipeline_check/steps/step.py
data_check/cli/__init__.py
data_check/cli/append.py
data_check/cli/common.py
data_check/cli/fake.py
data_check/cli/generate.py
data_check/cli/init.py
data_check/cli/load.py
data_check/cli/main.py
data_check/cli/ping.py
data_check/cli/run.py
data_check/cli/sql.py
data_check/fake/__init__.py
data_check/fake/column_config.py
data_check/fake/fake_config.py
data_check/fake/fake_data.py
data_check/fake/fake_iterator.py
data_check/fake/iterators/__init__.py
data_check/fake/iterators/dec.py
data_check/fake/iterators/inc.py
data_check/fake/iterators/random.py
data_check/output/__init__.py
data_check/output/diffed_df.py
data_check/output/handler.py
data_check/output/output.py
data_check/output/result_formatter.py
data_check-0.20.0.dist-info/licenses/LICENSE
data_check-0.20.0.dist-info/METADATA
data_check-0.20.0.dist-info/WHEEL
data_check-0.20.0.dist-info/entry_points.txt
data_check-0.20.0.dist-info/top_level.txt
data_check-0.20.0.dist-info/RECORD
