Metadata-Version: 2.4
Name: data_check
Version: 0.20.0
Summary: simple data validation
Author-email: Andreas Rjasanow <andrjas@gmail.com>
License-Expression: MIT
Project-URL: Homepage, https://andrjas.github.io/data_check/
Project-URL: Repository, https://github.com/andrjas/data_check
Keywords: data,validation,testing,quality
Classifier: Development Status :: 3 - Alpha
Classifier: Environment :: Console
Classifier: Intended Audience :: Developers
Classifier: Intended Audience :: Other Audience
Classifier: Intended Audience :: Science/Research
Classifier: Topic :: Database
Classifier: Topic :: Software Development
Classifier: Topic :: Software Development :: Testing
Requires-Python: <3.14,~=3.9
License-File: LICENSE
Requires-Dist: SQLAlchemy<3,>=2.0.19
Requires-Dist: pandas<3,>=2.2.1
Requires-Dist: pyyaml~=6.0
Requires-Dist: click<9,>=8.1.5
Requires-Dist: colorama<0.5,>=0.4.6
Requires-Dist: Jinja2<4,>=3.1.2
Requires-Dist: openpyxl<4,>=3.1.2
Requires-Dist: click-default-group<2,>=1.2.2
Requires-Dist: Faker>=37.1.0
Requires-Dist: pydantic<3,>=2
Provides-Extra: postgres
Requires-Dist: psycopg2-binary<3,>=2.9.6; extra == "postgres"
Provides-Extra: oracle
Requires-Dist: cx_Oracle<9,>=8.3.0; extra == "oracle"
Provides-Extra: oracledb
Requires-Dist: oracledb<4,>=3.1.0; extra == "oracledb"
Provides-Extra: mysql
Requires-Dist: pymysql[rsa]<2,>=1.1.0; extra == "mysql"
Provides-Extra: mssql
Requires-Dist: pyodbc<6,>=5; extra == "mssql"
Provides-Extra: duckdb
Requires-Dist: duckdb-engine<0.18,>=0.17.0; extra == "duckdb"
Provides-Extra: databricks
Requires-Dist: databricks-sqlalchemy<3,>=2.0.5; extra == "databricks"
Dynamic: license-file
